{
    "id": "dimensional_horrors",
    "name": "Dimensional Horrors",
    "author": "Caliallie#6369",
    "background": "Mutated servants of the dark gods able to materialize anywhere their influence is strong enough.",
    "units": {
        "greater_daemon_of_change": {
            "name": "Greater Daemon of Change",
            "description": "A large winged creature enlightened with extreme knowlege and magical powers by the dark god of change.",
            "subfactions": ["change"],
            "rules": [{"id": "leader_x", "x": "Infantry"}, "ambush", "fly", "stealth", {"id": "psychic", "x": 3}, "fear", {"id": "tough", "x": 2}],
            "min": 1,
            "max": 1,
            "category": "command",
            "keywords": ["monster"],
            "models": [
                {
                    "name": "Greater Daemon of Change",
                    "courage": 7,
                    "movement": 10,
                    "shoot": 7,
                    "fight": 7,
                    "defense": 10,
                    "reflexes": 7,
                    "weapons": ["exalted_staff_of_change"],
                    "options": [
                        {"replaceWeapon": "exalted_staff_of_change", "withWeapon": ["exalted_power_hammer", "exalted_power_spear"]},
                        {"limit": 1, "addWeapon": ["exalted_magic_beam", "exalted_magic_bolt", "change_blast"]}
                    ],
                    "min": 1,
                    "max": 1,
                    "rules": []
                }
            ]
        },
        "daemon_champion": {
            "name": "Daemon Champion",
            "subfactions": ["none", "change", "war", "pestilence", "excess"],
            "description": "A massive daemon gifted in the art of war.",
            "category": "command",
            "rules": [{"id": "leader_x", "x": "Infantry"}, "fear", {"id": "tough", "x": 1}, {"id": "wounds", "x": 3}],
            "keywords": ["monster"],
            "models": [
                {
                    "name": "Daemon Champion",
                    "movement": 6,
                    "courage": 7,
                    "shoot": 7,
                    "fight": 7,
                    "defense": 10,
                    "reflexes": 7,
                    "weapons": ["daemon_sword"],
                    "options": [
                        {"addRule": [{"id": "psychic", "x": 1}, {"id": "psychic", "x": 2}, {"id": "psychic", "x": 3}]},
                        {"replaceWeapon": "daemon_sword", "withWeapon": ["daemon_axe", "daemon_claws"]},
                        {"addRule": "wings"}
                    ],
                    "rules": [],
                    "min": 1,
                    "max": 1
                }
            ]
        },
        "champion_of_change": {
            "name": "Champion of Change",
            "description": "A frightening leader of the forces of change.",
            "subfactions": ["none", "change"],
            "category": "command",
            "rules": [{"id": "leader_x", "x": "Infantry"}, "stealth", {"id": "tough", "x": 1}, {"id": "psychic", "x": 1}],
            "keywords": ["infantry"],
            "models": [
                {
                    "name": "Champion of Change",
                    "movement": 6,
                    "courage": 6,
                    "shoot": 6,
                    "fight": 5,
                    "defense": 5,
                    "reflexes": 4,
                    "weapons": ["power_staff"],
                    "options": [
                        {"replaceWeapon": "power_staff", "withWeapon": "ritual_daggers"},
                        {"limit": 1, "addWeapon": ["magic_beam", "magic_bolt", "change_blast"]},
                        {"addRule": ["disk_of_change"]}
                    ],
                    "min": 1,
                    "max": 1,
                    "rules": []
                }
            ]
        },
        "champion_of_change_on_chariot": {
            "name": "Champion of Change on Chariot",
            "description": "A frightening leader of the forces of change riding a fearsome chariot pulled by magical lampries.",
            "subfactions": ["none", "change"],
            "category": "command",
            "rules": [{"id": "leader_x", "x": "Infantry"}, "stealth", {"id": "tough", "x": 1}, {"id": "psychic", "x": 1}, "hover"],
            "keywords": ["infantry"],
            "models": [
                {
                    "name": "Champion of Change on Chariot",
                    "movement": 10,
                    "courage": 6,
                    "shoot": 6,
                    "fight": 5,
                    "defense": 8,
                    "reflexes": 5,
                    "weapons": ["power_staff", {"id": "parasitic_bite", "count": 6}],
                    "options": [{"replaceWeapon": "power_staff", "withWeapon": "ritual_daggers"}, {"limit": 1, "addWeapon": ["magic_beam", "magic_bolt", "change_blast"]}],
                    "min": 1,
                    "max": 1,
                    "rules": []
                }
            ]
        },
        "blue_scholars": {
            "name": "Blue Scholars",
            "description": "Two enlightened blue daemons that travel the world collecting as m,uch new knowlege as they can.",
            "subfactions": ["none", "change"],
            "keywords": ["cavalry"],
            "category": "command",
            "min": 1,
            "max": 1,
            "rules": [{"id": "leader_x", "x": "Infantry"}, "stealth", {"id": "psychic", "x": 1}, {"id": "tough", "x": 1}, "hover", "psychic_syphon"],
            "models": [
                {"name": "Blue Scholars", "movement": 8, "courage": 6, "shoot": 5, "fight": 5, "defense": 5, "reflexes": 5, "weapons": ["quills", "disk_blades"], "min": 1, "max": 1, "rules": []}
            ]
        },
        "the_shifter": {
            "name": "The Shifter",
            "description": "A mysterious being able to morph its form into any other being. It enjoys using this ability to trick both enemies and foes with complicated pranks.",
            "subfactions": ["none", "change"],
            "keywords": ["infantry"],
            "category": "command",
            "min": 1,
            "max": 1,
            "rules": ["stealth", {"id": "tough", "x": 2}, {"id": "psychic", "x": 1}, "hover", {"id": "leader_x", "x": "Infantry"}],
            "models": [{"name": "The Shifter", "movement": 8, "courage": 6, "shoot": 6, "fight": 5, "defense": 6, "reflexes": 5, "weapons": ["tricksters_staff"], "min": 1, "max": 1, "rules": []}]
        },
        "chromatic_horrors": {
            "name": "Chromatic Horrors",
            "description": "Twisting warriors of change known for shifting forms before the very eyes of their victims.",
            "keywords": ["infantry"],
            "category": "core",
            "subfactions": ["none", "change"],
            "min": 10,
            "max": 30,
            "models": [
                {
                    "name": "Flame Warriors",
                    "rules": ["stealth"],
                    "movement": 6,
                    "courage": 5,
                    "shoot": 3,
                    "fight": 3,
                    "defense": 4,
                    "reflexes": 4,
                    "weapons": [{"id": "ccw", "count": 2}],
                    "options": [{"replaceModel": ["blue_warriors", "pink_warriors"]}],
                    "min": 10,
                    "max": 30
                }
            ]
        },
        "exalted_flame_daemon": {
            "name": "Exalted Flame Daemon",
            "description": "A daemon made of twisting, living flame held together by pure magic that acts as a leader for minor flame daemons.",
            "category": "specialist",
            "min": 1,
            "max": 1,
            "subfactions": ["none", "change"],
            "rules": [{"id": "tough", "x": 1}, "hover", "stealth"],
            "models": [
                {
                    "name": "Exalted Flame Daemon",
                    "movement": 8,
                    "courage": 6,
                    "shoot": 6,
                    "fight": 6,
                    "defense": 7,
                    "reflexes": 5,
                    "weapons": ["changing_flames", "flame_tongues"],
                    "min": 1,
                    "max": 1,
                    "rules": []
                }
            ]
        },
        "flame_daemon": {
            "name": "Flame Daemon",
            "description": "A shifting daemon of living flames.",
            "category": "specialist",
            "subfactions": ["none", "change"],
            "min": 3,
            "max": 9,
            "rules": ["stealth", "hover"],
            "models": [
                {
                    "name": "Flame Daemon",
                    "movement": 8,
                    "courage": 5,
                    "shoot": 6,
                    "fight": 4,
                    "defense": 7,
                    "reflexes": 4,
                    "weapons": ["flickering_flames", {"id": "ccw", "count": 2}],
                    "min": 3,
                    "max": 9,
                    "rules": []
                }
            ]
        },
        "manta_daemons": {
            "name": "Manta Daemons",
            "description": "Fast-flying manta-like daemons capable of close-range carnage.",
            "subfactions": ["none", "change"],
            "category": "strike",
            "min": 3,
            "max": 9,
            "rules": ["fly"],
            "models": [
                {"name": "Manta Daemon", "movement": 8, "courage": 5, "shoot": 4, "fight": 5, "defense": 7, "reflexes": 5, "weapons": [{"id": "parasitic_bite", "count": 3}], "min": 3, "max": 9}
            ]
        },
        "flame_chariot": {
            "name": "Flame Chariot",
            "description": "An intimidating construction of flame and manta daemons summoned to provide heavy support on the battlefeild.",
            "keywords": ["cavalry"],
            "subfactions": ["none", "change"],
            "category": "heavy",
            "min": 1,
            "max": 1,
            "rules": ["stealth", "fear", "hover"],
            "models": [
                {
                    "name": "Flame Chariot",
                    "movement": 10,
                    "courage": 6,
                    "shoot": 6,
                    "fight": 5,
                    "defense": 8,
                    "reflexes": 5,
                    "weapons": ["changing_flames", {"id": "parasitic_bite", "count": 6}, "flame_tongues"],
                    "options": [{"addRule": ["chanting_warriors"]}],
                    "min": 1,
                    "max": 1,
                    "rules": []
                }
            ]
        },
        "giant_daemon_spawn": {
            "name": "Giant Daemon Spawn",
            "description": "A giant mutated creature able to wreak havoc on the battlefeild.",
            "keywords": ["monster"],
            "subfactions": ["none", "change", "war", "pestilence", "excess"],
            "category": "heavy",
            "rules": ["agile", {"id": "resilient", "x": 3}],
            "min": 1,
            "max": 1,
            "models": [
                {
                    "name": "Giant Daemon Spawn",
                    "movement": 10,
                    "courage": 7,
                    "shoot": 4,
                    "fight": 5,
                    "defense": 8,
                    "reflexes": 8,
                    "weapons": ["fangs_and_claws"],
                    "min": 1,
                    "max": 1,
                    "rules": ["mutations"]
                }
            ]
        },
        "daemon_machine": {
            "name": "Daemon Machine",
            "decription": "An unholy melding of daemon and machine into a horrifying weapon.",
            "keywords": ["Vehicle"],
            "subfactions": ["none", "change", "war", "pestilence", "excess"],
            "category": "heavy",
            "rules": ["fear", "walker", "damage_table_vehicle"],
            "min": 1,
            "max": 1,
            "models": [
                {
                    "name": "Daemon Machine",
                    "movement": 8,
                    "courage": 5,
                    "shoot": 5,
                    "fight": 5,
                    "defense": 11,
                    "reflexes": 4,
                    "weapons": ["power_cannon", {"id": "power_claw", "count": 2}, {"id": "daemon_sword", "count": 3}, "phlegm_cannon"],
                    "options": [{"replaceWeapon": "daemon_sword", "withWeapon": "daemon_claw"}],
                    "min": 1,
                    "max": 1,
                    "rules": []
                }
            ]
        },
        "soul_mirror": {
            "name": "Soul Mirror",
            "description": "A contorted, corrupted mirror able to show its enemies their greatest fears.",
            "subfactions": ["none", "excess"],
            "keywords": ["cavalry"],
            "category": "command",
            "rules": [{"id": "leader_x", "x": "Infantry"}, {"id": "psychic", "x": 2}, {"id": "resilient", "x": 1}, "no_escape"],
            "min": 1,
            "max": 1,
            "models": [
                {
                    "name": "Soul Mirror",
                    "movement": 10,
                    "courage": 6,
                    "shoot": 7,
                    "fight": 7,
                    "defense": 7,
                    "reflexes": 5,
                    "weapons": [{"id": "lashing_tentacles", "count": 2}, {"id": "sweeping_claws", "count": 6}],
                    "min": 1,
                    "max": 1,
                    "rules": []
                }
            ]
        },
        "excess_champion": {
            "name": "Excess Champion",
            "description": "A leader of the forces of excess.",
            "subfactions": ["none", "excess"],
            "keywords": ["infantry"],
            "category": "command",
            "rules": [{"id": "leader_x", "x": "Infantry"}, {"id": "psychic", "x": 1}, {"id": "resilient", "x": 1}],
            "min": 1,
            "max": 1,
            "models": [
                {
                    "name": "Excess Champion",
                    "movement": 7,
                    "courage": 6,
                    "shoot": 7,
                    "fight": 7,
                    "defense": 5,
                    "reflexes": 5,
                    "weapons": [{"id": "sweeping_claws", "count": 3}],
                    "min": 1,
                    "max": 1,
                    "rules": []
                }
            ]
        },
        "excess_champion_on_exalted_chariot": {
            "name": "Excess Champion on Exalted Chariot",
            "decription": "A leader of the forces of excess on a contorted chariot.",
            "subfactions": ["none", "excess"],
            "keywords": ["cavalry"],
            "category": "command",
            "rules": [{"id": "leader_x", "x": "Infantry"}, {"id": "psychic", "x": 1}, {"id": "resilient", "x": 1}, {"id": "impact", "x": 2}],
            "min": 1,
            "max": 1,
            "models": [
                {
                    "name": "Excess Champion on Exalted Chariot",
                    "movement": 10,
                    "courage": 6,
                    "shoot": 7,
                    "fight": 7,
                    "defense": 8,
                    "reflexes": 5,
                    "weapons": [{"id": "lashing_tentacles", "count": 2}, {"id": "sweeping_claws", "count": 6}],
                    "options": [{"addWeapon": "tormenting_whips"}],
                    "min": 1,
                    "max": 1,
                    "rules": []
                }
            ]
        },
        "excess_champion_reaper_chariot": {
            "name": "Excess Champion on Reaper Chariot",
            "description": "A leader of the forces of excess on a bladed chariot made to reap souls on the battlefeild.",
            "subfactions": ["none", "excess"],
            "keywords": ["cavalry"],
            "category": "command",
            "rules": [{"id": "leader_x", "x": "Infantry"}, {"id": "psychic", "x": 1}, {"id": "resilient", "x": 1}],
            "min": 1,
            "max": 1,
            "models": [
                {
                    "name": "Excess Champion on Reaper Chariot",
                    "movement": 10,
                    "courage": 6,
                    "shoot": 7,
                    "fight": 7,
                    "defense": 8,
                    "reflexes": 5,
                    "weapons": [{"id": "lashing_tentacles", "count": 2}, {"id": "sweeping_claws", "count": 6}, "reaper_axle"],
                    "options": [{"addWeapon": "tormenting_whips"}],
                    "min": 1,
                    "max": 1,
                    "rules": []
                }
            ]
        },
        "excess_champion_on_chariot": {
            "name": "Excess Champion on Chariot",
            "decription": "A leader of the forces of excess on a contorted chariot.",
            "subfactions": ["none", "excess"],
            "keywords": ["cavalry"],
            "category": "command",
            "rules": [{"id": "leader_x", "x": "Infantry"}, {"id": "psychic", "x": 1}, {"id": "resilient", "x": 1}, {"id": "impact", "x": 2}],
            "min": 1,
            "max": 1,
            "models": [
                {
                    "name": "Excess Champion on Chariot",
                    "movement": 10,
                    "courage": 6,
                    "shoot": 7,
                    "fight": 7,
                    "defense": 8,
                    "reflexes": 5,
                    "weapons": [{"id": "lashing_tentacles", "count": 2}, {"id": "sweeping_claws", "count": 6}],
                    "options": [{"addWeapon": "tormenting_whips"}],
                    "min": 1,
                    "max": 1,
                    "rules": []
                }
            ]
        },
        "beguiling_harpist": {
            "name": "Beguiling Harpist",
            "description": "A horribly alluring commander of the forces of excess that plays enthralling melodies on a harp made from her enemies.",
            "subfactions": ["none", "excess"],
            "keywords": ["infantry"],
            "category": "command",
            "rules": [{"id": "leader_x", "x": "Infantry"}, {"id": "resilient", "x": 1}, "psychic_syphon"],
            "min": 1,
            "max": 1,
            "models": [
                {
                    "name": "Beguiling Harpist",
                    "movement": 7,
                    "courage": 6,
                    "shoot": 7,
                    "fight": 7,
                    "defense": 5,
                    "reflexes": 5,
                    "weapons": ["enrapturing_lyre", {"id": "sweeping_claws", "count": 3}],
                    "min": 1,
                    "max": 1,
                    "rules": []
                }
            ]
        },
        "greater_daemon_of_excess": {
            "name": "Greater Daemon of Excess",
            "description": "An enlightened daemon of excess equally capable of leading forces and devestating enemies.",
            "subfactions": ["excess"],
            "keywords": ["monster"],
            "category": "command",
            "rules": [{"id": "leader_x", "x": "Infantry"}, {"id": "resilient", "x": 2}, "stealth", {"id": "psychic", "x": 2}],
            "min": 1,
            "max": 1,
            "models": [
                {
                    "name": "Greater Daemon of Excess",
                    "movement": 12,
                    "courage": 7,
                    "shoot": 8,
                    "fight": 8,
                    "defense": 9,
                    "reflexes": 7,
                    "weapons": ["splitting_claws", "souleating_sword"],
                    "options": [{"addRule": ["ritual_dagger", "glittering_sheild", "menacing_hand"]}, {"addWeapon": ["living_whip"]}],
                    "min": 1,
                    "max": 1
                }
            ]
        },
        "deadly_duo": {
            "name": "Deadly Duo",
            "description": "Two excess daemons fused in horribly beautiful synchrony.",
            "subfactions": ["none", "excess"],
            "keywords": ["monster"],
            "category": "command",
            "rules": [{"id": "leader_x", "x": "Infantry"}, {"id": "resilient", "x": 1}, {"id": "psychic", "x": 1}],
            "min": 1,
            "max": 1,
            "models": [
                {"name": "Deadly Duo", "movement": 8, "courage": 7, "shoot": 8, "fight": 8, "defense": 9, "reflexes": 5, "weapons": ["daemon_axe", "tormenting_whip"], "min": 1, "max": 1, "rules": []}
            ]
        },
        "mask_of_excess": {
            "name": "Mask of Excess",
            "description": "A phantasmic daemon summoned to the battlefield by the forces of excess.",
            "subfactions": ["none", "excess"],
            "keywords": ["infantry"],
            "category": "command",
            "rules": [{"id": "leader_x", "x": "Infantry"}, {"id": "resilient", "x": 1}, "agile", "stealth"],
            "min": 1,
            "max": 1,
            "models": [{"name": "Mask of Excess", "movement": 8, "courage": 6, "shoot": 7, "fight": 7, "defense": 5, "reflexes": 5, "weapons": ["segmented_claws"], "min": 1, "max": 1, "rules": []}]
        },
        "excess_warriors": {
            "name": "Excess Warriors",
            "description": "The main bulk of the forces of excess, these equally alluring and devastating warriors find pleasure in the pain they inflict on the battlefield.",
            "subfactions": ["none", "excess"],
            "keywords": ["infantry"],
            "category": "core",
            "min": 10,
            "max": 30,
            "models": [
                {
                    "name": "Siren",
                    "movement": 7,
                    "courage": 5,
                    "shoot": 6,
                    "fight": 6,
                    "defense": 5,
                    "reflexes": 5,
                    "weapons": [{"id": "sweeping_claws", "count": 2}],
                    "options": [{"limit": 1, "addRule": ["horrible_icon", "instrument_of_excess", "banner_of_excess"]}],
                    "min": 1,
                    "max": 1
                },
                {"name": "Excess Warrior", "movement": 7, "courage": 5, "shoot": 6, "fight": 6, "defense": 5, "reflexes": 5, "weapons": [{"id": "sweeping_claws", "count": 2}], "min": 9, "max": 29}
            ]
        },
        "excess_steed": {
            "name": "Excess Steed",
            "description": "A seductively mutated beast able to ferry forces fo slaanesh into battle or fight on their own.",
            "keywords": ["cavalry"],
            "subfactions": ["none", "excess"],
            "category": "specialist",
            "rules": ["agile"],
            "min": 1,
            "max": 9,
            "models": [
                {
                    "name": "Excess Steed",
                    "movement": 8,
                    "courage": 5,
                    "shoot": 4,
                    "fight": 6,
                    "defense": 6,
                    "reflexes": 5,
                    "weapons": [{"id": "sweeping_claws", "count": 4}, "barbed_tail"],
                    "options": [{"modelLimit": 1, "addWeapon": ["sweeping_claws"]}],
                    "min": 1,
                    "max": 9,
                    "rules": ["psychic_syphon", {"id": "wounds", "x": 2}]
                }
            ]
        },
        "gargoyles": {
            "name": "Gargoyles",
            "description": "Horrible winged demons able to be summoned to assist any of the demon factions.",
            "keywords": ["infantry"],
            "subfactions": ["none", "change", "war", "pestilence", "excess"],
            "category": "strike",
            "rules": ["fly", "fear"],
            "min": 5,
            "max": 20,
            "models": [
                {"name": "Gargoyle", "movement": 10, "courage": 4, "shoot": 4, "fight": 5, "defense": 5, "reflexes": 4, "weapons": [{"id": "ccw", "count": 2}], "min": 5, "max": 20, "rules": []}
            ]
        },
        "reaper_chariot": {
            "name": "Reaper Chariot",
            "description": "A bladed chariot made to reap souls on the battlefeild.",
            "subfactions": ["none", "change", "war", "pestilence", "excess"],
            "keywords": ["cavalry"],
            "category": "command",
            "rules": [],
            "min": 1,
            "max": 1,
            "models": [
                {
                    "name": "Reaper Chariot",
                    "movement": 10,
                    "courage": 6,
                    "shoot": 6,
                    "fight": 6,
                    "defense": 8,
                    "reflexes": 5,
                    "weapons": [{"id": "lashing_tentacles", "count": 2}, {"id": "sweeping_claws", "count": 6}, "reaper_axle"],
                    "options": [{"addWeapon": "tormenting_whips"}],
                    "min": 1,
                    "max": 1,
                    "rules": []
                }
            ]
        },
        "excess_warriors_on_steeds": {
            "name": "Excess Warriors on Steeds",
            "description": "A seductively mutated beast able to ferring forces of slaanesh into battle.",
            "keywords": ["cavalry"],
            "category": "strike",
            "rules": ["agile"],
            "subfactions": ["none", "excess"],
            "min": 5,
            "max": 20,
            "models": [
                {
                    "name": "Deathseeker",
                    "movement": 8,
                    "courage": 5,
                    "shoot": 6,
                    "fight": 6,
                    "defense": 5,
                    "reflexes": 5,
                    "weapons": [{"id": "sweeping_claws", "count": 2}, {"id": "lashing_tentacles"}],
                    "options": [{"limit": 1, "addRule": ["horrible_icon", "instrument_of_excess", "banner_of_excess"]}],
                    "min": 1,
                    "max": 1,
                    "rules": []
                },
                {
                    "name": "Excess Steed",
                    "movement": 8,
                    "courage": 5,
                    "shoot": 6,
                    "fight": 6,
                    "defense": 5,
                    "reflexes": 5,
                    "weapons": [{"id": "sweeping_claws", "count": 2}, {"id": "lashing_tentacles"}],
                    "min": 4,
                    "max": 19,
                    "rules": []
                }
            ]
        },
        "warleader_champion": {
            "name": "Warleader Champion",
            "description": "The greatest of the war-god's tacticians, chosen to lead his forces to battle",
            "keywords": ["infantry"],
            "category": "command",
            "rules": [],
            "subfaction": ["war"],
            "min": 1,
            "max": 1,
            "models": [
                {
                    "name": "Warleader Champion",
                    "movement": 6,
                    "courage": 6,
                    "shoot": 5,
                    "fight": 8,
                    "defense": 5,
                    "reflexes": 5,
                    "weapons": [{"id": "war_sword", "count": 4}],
                    "rules": [{"id": "leader", "x": "Infantry"}, {"id": "warrior_tactics", "x": 1}, {"id": "wounds", "x": 2}],
                    "options": [{"replaceRule": {"id": "warrior_tactics", "x": 1}, "withRule": {"id": "warrior_tactics", "x": 2}}]
                }
            ]
        },
        "warleader_throne": {
            "name": "Warleader Champion on Skull Throne",
            "description": "A great general of the war-god, atop a throne befitting his status",
            "keywords": ["cavalry"],
            "category": "command",
            "rules": [],
            "subfaction": ["war"],
            "min": 1,
            "max": 1,
            "models": [
                {
                    "name": "Warleader Champion on Skull Throne",
                    "movement": 8,
                    "courage": 6,
                    "shoot": 5,
                    "fight": 8,
                    "defense": 11,
                    "rules": [{"id": "impact", "x": 2}, "damage_table_vehicle", {"id": "leader", "x": "Infantry"}, {"id": "warrior_tactics", "x": 2}],
                    "weapons": [{"id": "war_sword", "count": 6}, {"id": "throne_mouth", "count": 2}]
                }
            ]
        },
        "wrath_dogs": {
            "name": "Wrath Dogs",
            "description": "Cry havoc!  The dogs of war bite seek only to tear their master's foes asunder.",
            "keywords": ["cavalry"],
            "category": "strike",
            "rules": [],
            "subfaction": ["war"],
            "min": 5,
            "max": 10,
            "models": [
                {"name": "Dogs of War", "movement": 8, "courage": 6, "shoot": 5, "fight": 8, "defense": 6, "min": 5, "max": 20, "rules": ["ward"], "weapons": [{"id": "hounds_teeth", "count": 4}]}
            ]
        },
        "wrath_warriors": {
            "name": "Wrath Warriors",
            "description": ["Minions of the war-god, these ferocious demons know no rest, only battle."],
            "keywords": ["infantry"],
            "category": "core",
            "subfactions": ["war"],
            "min": 10,
            "max": 30,
            "models": [
                {"name": "Reaper", "movement": 6, "courage": 5, "shoot": 6, "fight": 7, "defense": 5, "reflexes": 5, "min": 1, "max": 1, "weapons": [{"id": "war_sword", "count": 2}]},
                {
                    "name": "Warrior",
                    "movement": 6,
                    "courage": 5,
                    "shoot": 6,
                    "fight": 7,
                    "defense": 5,
                    "reflexes": 5,
                    "min": 9,
                    "max": 29,
                    "weapons": [{"id": "war_sword", "count": 1}],
                    "options": [{"modelLimit": 1, "addRule": ["banner_of_blood"]}, {"modelLimit": 1, "addRule": ["instrument_of_blood"]}, {"modelLimit": 1, "addRule": ["horrible_icon"]}]
                }
            ]
        },
        "wrath_monger": {
            "name": "Greater Daemon of War",
            "description": "The war-god's most exalted warriors are granted the strongest bodies",
            "keywords": ["monster"],
            "category": "command",
            "subfactions": "war",
            "models": [
                {
                    "name": "Greater Daemon of War",
                    "movement": 12,
                    "courage": 7,
                    "shoot": 5,
                    "fight": 8,
                    "defense": 11,
                    "reflexes": 7,
                    "min": 1,
                    "max": 1,
                    "weapons": [{"id": "blessed_axe", "count": 6}, {"id": "blessed_whip", "count": 1}],
                    "rules": ["fly", {"id": "leader_x", "x": "Infantry"}, "ambush", {"id": "tough", "x": 2}, "damage_table_monster"],
                    "options": [{"replaceWeapon": ["blessed_axe", "blessed_whip"], "withWeapon": {"id": "blessed_greataxe", "count": 6}}]
                }
            ]

        }
    },
    "models": {
        "pink_warriors": {
            "name": "Pink Warriors",
            "movement": 6,
            "courage": 5,
            "shoot": 5,
            "fight": 5,
            "defense": 6,
            "reflexes": 4,
            "weapons": ["twisting_flames", "ccw"],
            "options": [
                {"modelLimit": 1, "addRule": ["banner_of_change"]},
                {"modelLimit": 1, "addRule": ["instrument_of_change"]},
                {"modelLimit": 1, "addRule": ["horrible_icon"]},
                {"modelLimit": 1, "addRule": [{"id": "psychic", "x": 1}]}
            ],
            "min": 10,
            "max": 30,
            "rules": []
        },
        "blue_warriors": {"name": "Blue Warriors", "movement": 6, "courage": 5, "shoot": 4, "fight": 4, "defense": 5, "reflexes": 4, "weapons": ["ccw"], "min": 0, "max": 30, "rules": []}
    },
    "weapons": {
        "exalted_staff_of_change": {"name": "Exalted Staff of Change", "attacks": 5, "short": "Melee", "ap": 4},
        "exalted_power_hammer": {"name": "Exalted Power Hammer", "attacks": 4, "short": "Melee", "ap": 5},
        "exalted_power_spear": {"name": "Exalted Power Spear", "attacks": 3, "short": "Melee", "ap": 7},
        "exalted_magic_beam": {"name": "Exalted Magic Beam", "attacks": 6, "short": 6, "medium": 12, "ap": 2},
        "exalted_magic_bolt": {"name": "Exalted Magic Bolt", "attacks": 3, "short": 6, "medium": 12, "ap": 5},
        "change_blast": {"name": "Change Blast", "attacks": 1, "short": 9, "medium": 18, "ap": 7},
        "power_staff": {"name": "Power Staff", "attacks": 2, "short": "Melee", "ap": 2},
        "ritual_daggers": {"name": "Ritual Daggers", "attacks": 2, "short": "Melee"},
        "magic_beam": {"name": "Magic Beam", "attacks": 2, "short": 6, "ap": 4},
        "magic_bolt": {"name": "Magic Beam", "attacks": 2, "short": 6, "medium": 12, "ap": 4},
        "parasitic_bite": {"name": "Parasitic Bite", "attacks": 1, "short": "Melee", "ap": 4},
        "quills": {"name": "Quills", "attacks": 2, "short": "Melee"},
        "disk_blades": {"name": "Disk Blades", "attacks": 2, "short": "Melee", "ap": 1},
        "tricksters_staff": {
            "name": "Trickster's Staff",
            "profiles": [
                {"name": "Staff Form", "attacks": 6, "short": "Melee"},
                {"name": "Sword Form", "attacks": 4, "short": "Melee", "ap": 5},
                {"name": "Hammer Form", "attacks": 2, "short": "Melee", "ap": 7}
            ]
        },
        "magical_ccw": {"name": "Magical CCW", "attacks": 1, "short": "Melee", "ap": 4, "rules": ["rending"]},
        "twisting_flames": {"name": "Twisting Flames", "attacks": 2, "short": 9, "medium": 18, "rules": ["flame"]},
        "changing_flames": {
            "name": "Changing Flames",
            "profiles": [
                {"name": "Blue Flame", "attacks": 3, "short": 9, "medium": 18, "ap": 7, "rules": ["flame"]},
                {"name": "Pink Flame", "attacks": 6, "short": 6, "medium": 12, "ap": 3, "rules": ["flame"]}
            ]
        },
        "flame_tongues": {"name": "Flame Tongues", "attacks": 3, "short": "Melee", "ap": 2},
        "flickering_flames": {"name": "Flickering Flames", "attacks": 3, "short": 6, "medium": 12, "ap": 1, "rules": ["pistol", "flame"]},
        "fangs_and_claws": {"name": "Fangs and Claws", "attacks": 9, "short": "Melee", "ap": 7},
        "power_cannon": {"name": "Power Cannon", "attacks": 3, "short": 24, "medium": 48, "ap": 4},
        "power_claw": {"name": "Power Claw", "attacks": 1, "short": "Melee", "ap": 6},
        "phlegm_cannon": {"name": "Phlegm Cannon", "attacks": 1, "short": 18, "medium": 36, "ap": 6, "rules": [{"id": "blast", "x": 3}]},
        "daemon_claw": {"name": "Daemon Claw", "attacks": 10, "short": "Melee", "ap": 6},
        "lashing_tentacles": {"name": "Lashing Tentacles", "attacks": 1, "short": "Melee", "ap": 3},
        "sweeping_claws": {"name": "Sweeping Claws", "attacks": 1, "short": "Melee", "ap": 0, "rules": ["rending"]},
        "tormenting_whips": {"name": "Tormenting Whips", "attacks": 3, "short": 6, "ap": 1, "rules": ["pistol"]},
        "reaper_axle": {"name": "Reaper Axle", "attacks": 5, "short": "Melee", "ap": 5},
        "enrapturing_lyre": {
            "name": "Enrapturing Lyre",
            "profiles": [{"name": "Raucous Melody", "attacks": 6, "short": 9, "medium": 18, "ap": 1}, {"name": "Melodious Blast", "attacks": 1, "short": 12, "medium": 24, "ap": 6}]
        },
        "splitting_claws": {"name": "Splitting Claws", "attacks": 6, "short": "Melee", "ap": 4, "rules": ["rending"]},
        "souleating_sword": {"name": "Soul-eating Sword", "attacks": 6, "short": "Melee", "ap": 6},
        "living_whip": {"name": "Living Whip", "attacks": 6, "short": 6, "ap": 4},
        "tormenting_whip": {
            "name": "Tormenting Whip",
            "profiles": [{"name": "Melee", "attacks": 8, "short": "Melee", "ap": 1, "rules": ["blast"]}, {"name": "Shooting", "attacks": 3, "short": 6, "ap": 2}]
        },
        "segmented_claws": {"name": "Segmented Claws", "attacks": 5, "short": "Melee", "ap": 2, "rules": ["rending"]},
        "barbed_tail": {"name": "Barbed Tail", "attacks": 1, "short": "Melee", "ap": 2},
        "war_sword": {"name": "War-Blessed Sword", "attacks": 1, "short": "Melee", "ap": 2, "rules": ["rending"]},
        "throne_mouth": {"name": "War-Throne's Mashing Gnaw", "attacks": 1, "short": "Melee", "ap": 3},
        "hounds_teeth": {"name": "Hound's Jaws", "attacks": 1, "short": "Melee", "ap": 1},
        "blessed_axe": {"name": "War-Blessed Axe", "attacks": 1, "short": "Melee", "ap": 8},
        "blessed_whip": {"name": "War-Blessed Whip", "attacks": 1, "short": 6, "medium": 12, "ap": 5, "rules": ["pistol"]},
        "blessed_greataxe": {"name": "War-Blessed Greataxe", 
            "profiles": [{"name": "Sweeping Attack", "attacks": 2, "short": "Melee", "ap": 5},
                        {"name": "Mighty Strike", "attacks": 1, "short": "Melee", "ap": "12"}]
            }
    },
    "rules": {
        "psychic_syphon": {"name": "Psychic Syphon", "description": "Enemy models within 12\" of this model suffer -1 to their psychic tests.", "points": 5},
        "banner_of_change": {"name": "Banner of Change", "hidden": true, "description_short": "+1 Courage", "description": "+1 Courage.", "points": 20},
        "horrible_icon": {
            "name": "Horrible Icon",
            "description": "At any point during this unit's activation, roll 9 dice. For each roll of 1 or 2 the closest enemy unit within 9\" takes one automatic hit with AP -2.",
            "points": 20
        },
        "instrument_of_change": {"name": "Instrument of Change", "description": "Models in this unit get +1\" of Movement.", "points": 5},
        "chanting_warriors": {"name": "Chanting Warriors", "description": "Enemy units must subtract one from psychic tests within 9\" of this model.", "points": 5},
        "no_escape": {
            "name": "No Escape",
            "description": "Enemy units attempting to fall back from this unit take their Initiative test at -2.",
            "effects": [{"type": "alterStat", "statName": "reflexes", "target": "enemy", "value": 2, "frequency": 5}]
        },
        "ritual_dagger": {"name": "Ritual Dagger", "description": "After this model fights in Melee, one enemy unit in its engagement range takes 2 automatic hits."},
        "glittering_sheild": {"name": "Glittering Sheild", "description": "This model gains Resilient(+1).", "points": 2},
        "menacing_hand": {"name": "Menacing Hand", "description": "After this model fights, if any non-vehicle model was slain by this model, this model regains 2 lost wounds."},
        "instrument_of_excess": {"name": "Instrument of Excess", "description": "Add 1 to this unit's movement characteristic.", "points": 10},
        "banner_of_excess": {"name": "Banner of Excess", "description": "This unit may re-roll failed Strength rolls of 1 or 2.", "points": 20},
        "instrument_of_blood": {"name": "Instrument of War", "description": "This unit has +2 Courage while within 3\" of any enemy units", "points": 10},
        "banner_of_blood": {"name": "Banner of Blood", "description": "This unit may add 2\" to its movement when Charging", "points": 20},
        "wings": {
            "name": "Daemon Wings",
            "hidden": true,
            "description": "Increases movement to 8 inches. Gives the model fly and ambush.",
            "description_short": "Fly, Ambush, 8\" Move",
            "effects": [{"type": "alterStat", "statName": "movement", "value": 8}, {"type": "grantRule", "rule": "fly"}, {"type": "grantRule", "rule": "ambush"}]
        },
        "warrior_tactics": {
            "name": "War-God Tactics",
            "inputs": ["x"],
            "description": "When this unit is activated, choose up to X friendly _Infantry_ units within 6\". Those units may re-roll failed Strength tests of 9+ until the end of the round.",
            "points": ["rule.x", {"multiply": 10}]
        }
    },
    "strategies": {},
    "powers": {}
}